{
  "type": "FeatureCollection",
  "features": [
    {
      "type": "Feature",
      "properties": {
        "name": "Site #12 (Waterfront)",
        "price": "$35/night",
        "desc": "Direct lake access. Perfect for kayaks.",
        "size": "40ft RV",
        "image": "https://images.unsplash.com/photo-1478131143081-80f7f84ca84d?auto=format&fit=crop&w=600&q=80"
      },
      "geometry": { "type": "Point", "coordinates": [-83.0785, 34.4985] }
    },
    {
      "type": "Feature",
      "properties": {
        "name": "Site #14 (Secluded)",
        "price": "$30/night",
        "desc": "Tucked back in the pines.",
        "size": "Tent Only",
        "image": "https://images.unsplash.com/photo-1523987355523-c7b5b0dd90a7?auto=format&fit=crop&w=600&q=80"
      },
      "geometry": { "type": "Point", "coordinates": [-83.0772, 34.4990] }
    }
  ]
}
