{
  "type": "FeatureCollection",
  "features": [
    {
      "type": "Feature",
      "properties": {
        "name": "Site 133",
        "price": "$30/night",
        "desc": "Great view of the lake, close to the bathhouse.",
        "size": "Tent/RV",
        "image": "https://images.unsplash.com/photo-1523987355523-c7b5b0dd90a7?auto=format&fit=crop&w=600&q=80"
      },
      "geometry": {
        "type": "Point",
        "coordinates": [-83.056539, 34.499855]
      }
    }
  ]
}
